files/__init__.py
random_name_generator/__init__.py
random_name_generator/resources/__init__.py
random_name_generator/resources/adjectives.txt
random_name_generator/resources/latin_adjectives.txt
random_name_generator/resources/latin_nouns.txt
random_name_generator/resources/name_generator.py
random_name_generator/resources/nouns.py
random_name_generator/resources/nouns.txt
random_name_generator/resources/sicilian_nouns.txt
random_name_generator-1.0.7.data/data/random_name_generator/adjectives.txt
random_name_generator-1.0.7.data/data/random_name_generator/latin_adjectives.txt
random_name_generator-1.0.7.data/data/random_name_generator/latin_nouns.txt
random_name_generator-1.0.7.data/data/random_name_generator/nouns.txt
random_name_generator-1.0.7.data/data/random_name_generator/sicilian_nouns.txt
random_name_generator-1.0.7.dist-info/METADATA
random_name_generator-1.0.7.dist-info/RECORD
random_name_generator-1.0.7.dist-info/WHEEL
random_name_generator-1.0.7.dist-info/top_level.txt
